setup.py
sqliteutil/DBUtil.py
sqliteutil/__init__.py
sqliteutil.egg-info/PKG-INFO
sqliteutil.egg-info/SOURCES.txt
sqliteutil.egg-info/dependency_links.txt
sqliteutil.egg-info/top_level.txt