Metadata-Version: 1.0
Name: sqliteutil
Version: 1.0.2
Summary: util for sqlite
Home-page: UNKNOWN
Author: UNKNOWN
Author-email: UNKNOWN
License: MIT
Platform: UNKNOWN
